MANIFEST.in
Makefile
README.rst
__init__.py
setup.cfg
setup.py
jinja_kit/__init__.py
jinja_kit/core.py
jinja_kit/exceptions.py
jinja_kit/utils.py
jinja_kit.egg-info/PKG-INFO
jinja_kit.egg-info/SOURCES.txt
jinja_kit.egg-info/dependency_links.txt
jinja_kit.egg-info/requires.txt
jinja_kit.egg-info/top_level.txt
jinja_kit/contrib/__init__.py
jinja_kit/contrib/django/__init__.py
jinja_kit/contrib/django/decorators.py
jinja_kit/contrib/django/defaults.py
jinja_kit/contrib/django/ext.py
jinja_kit/contrib/django/filters.py
jinja_kit/contrib/django/globals.py
jinja_kit/contrib/django/response.py