Metadata-Version: 1.1
Name: jinja-kit
Version: 0.0.16
Summary: Collection of utilities and extenstion for jinja2
Home-page: https://github.com/lispython/jinja-kit
Author: Alexandr Lispython
Author-email: alex@obout.ru
License: BSD
Platform: Linux
Platform: Mac
Classifier: Development Status :: 5 - Production/Stable
Classifier: Environment :: Web Environment
Classifier: Intended Audience :: Developers
Classifier: License :: OSI Approved :: BSD License
Classifier: Operating System :: OS Independent
Classifier: Programming Language :: Python
Classifier: Programming Language :: Python :: 3
Classifier: Topic :: Internet :: WWW/HTTP :: Dynamic Content
Classifier: Topic :: Software Development :: Libraries :: Python Modules
Classifier: Topic :: Text Processing :: Markup :: HTML
